{
    "anointable":  true,
    "description":  "Your creatures deal additional damage equal to \u003c2\u003e% of the amount of damage they\u0027ve dealt with [life_paladin_retribution] Retribution in the current battle.",
    "icon":  "images/perk/Crusade.png",
    "id":  136,
    "maxRanks":  50,
    "name":  "Crusade",
    "notes":  [

              ],
    "pointsPerRank":  2,
    "specialization":  10,
    "$schema":  "https://github.com/iconmaster5326/SiralimJSON/blob/main/schema/perk.yaml"
}
