{
    "anointable":  true,
    "description":  "When your creatures damage an enemy, they deal \u003c1\u003e% more damage for each other creature between the two creatures on the {TIMELINE}.",
    "icon":  "images/perk/GravitysVoid.png",
    "id":  176,
    "maxRanks":  15,
    "name":  "Gravity\u0027s Void",
    "notes":  [

              ],
    "pointsPerRank":  10,
    "specialization":  12,
    "$schema":  "https://github.com/iconmaster5326/SiralimJSON/blob/main/schema/perk.yaml"
}
