{
    "category":  "misc",
    "collision":  "fullTall",
    "creator":  null,
    "height":  1,
    "id":  1518,
    "maxCount":  null,
    "name":  "Ancient Fish Tank",
    "notes":  [

              ],
    "sources":  [
                    {
                        "type":  "everett"
                    }
                ],
    "sprite":  "images/decoration/AncientFishTank.png",
    "visible":  true,
    "width":  2,
    "$schema":  "https://github.com/iconmaster5326/SiralimJSON/blob/main/schema/decoration.yaml"
}
