{
    "category":  "misc",
    "collision":  "none",
    "creator":  null,
    "height":  0,
    "id":  1788,
    "maxCount":  null,
    "name":  "Damarel Wire (2)",
    "notes":  [

              ],
    "sources":  [
                    {
                        "type":  "everett"
                    }
                ],
    "sprite":  "images/decoration/DamarelWire2.png",
    "visible":  true,
    "width":  0,
    "$schema":  "https://github.com/iconmaster5326/SiralimJSON/blob/main/schema/decoration.yaml"
}
