{
    "category":  "altar",
    "collision":  "fullTall",
    "creator":  null,
    "height":  1,
    "id":  2057,
    "maxCount":  1,
    "name":  "Realm Altar of Muse",
    "notes":  [

              ],
    "sources":  [
                    {
                        "cost":  5,
                        "rank":  60,
                        "realm":  31,
                        "type":  "godshop"
                    }
                ],
    "sprite":  "images/decoration/RealmAltarofMuse.png",
    "visible":  true,
    "width":  1,
    "$schema":  "https://github.com/iconmaster5326/SiralimJSON/blob/main/schema/decoration.yaml"
}
