{
    "battleSprite":  "images/skin/Archmage/battle.png",
    "creator":  null,
    "creature":  740,
    "id":  372,
    "name":  "Archmage",
    "notes":  [

              ],
    "overworldSprite":  {
                            "east":  [
                                         "images/skin/Archmage/overworld_e0.png",
                                         "images/skin/Archmage/overworld_e1.png"
                                     ],
                            "north":  [
                                          "images/skin/Archmage/overworld_n0.png",
                                          "images/skin/Archmage/overworld_n1.png"
                                      ],
                            "south":  [
                                          "images/skin/Archmage/overworld_s0.png",
                                          "images/skin/Archmage/overworld_s1.png"
                                      ],
                            "west":  [
                                         "images/skin/Archmage/overworld_w0.png",
                                         "images/skin/Archmage/overworld_w1.png"
                                     ]
                        },
    "race":  null,
    "reserved":  false,
    "sources":  [
                    {
                        "type":  "random"
                    }
                ],
    "$schema":  "https://github.com/iconmaster5326/SiralimJSON/blob/main/schema/skin.yaml"
}
