{
    "battleSprite":  "images/skin/RuneKnight/battle.png",
    "creator":  null,
    "creature":  null,
    "id":  517,
    "name":  "Rune Knight",
    "notes":  [

              ],
    "overworldSprite":  {
                            "east":  [
                                         "images/skin/RuneKnight/overworld_e0.png",
                                         "images/skin/RuneKnight/overworld_e1.png"
                                     ],
                            "north":  [
                                          "images/skin/RuneKnight/overworld_n0.png",
                                          "images/skin/RuneKnight/overworld_n1.png"
                                      ],
                            "south":  [
                                          "images/skin/RuneKnight/overworld_s0.png",
                                          "images/skin/RuneKnight/overworld_s1.png"
                                      ],
                            "west":  [
                                         "images/skin/RuneKnight/overworld_w0.png",
                                         "images/skin/RuneKnight/overworld_w1.png"
                                     ]
                        },
    "race":  "Hemomancer",
    "reserved":  true,
    "sources":  [

                ],
    "$schema":  "https://github.com/iconmaster5326/SiralimJSON/blob/main/schema/skin.yaml"
}
