{
    "condition":  null,
    "creator":  null,
    "description":  "Socket an Artifact\u0027s [slot_trait] Trait Slot with this item to gain this trait:\\n\\nCrab Trap:\nAfter this creature is {ACTION_attacked} while it is {ACTION_defending}, it reduces the enemy\u0027s {STAT_defense} and {STAT_speed} by 35%.",
    "icon":  "images/item/material/ButteryBait.png",
    "id":  1440,
    "name":  "Buttery Bait",
    "notes":  [

              ],
    "slot":  "trait",
    "sources":  [
                    {
                        "type":  "random"
                    }
                ],
    "stats":  [

              ],
    "trait":  1748,
    "$schema":  "https://github.com/iconmaster5326/SiralimJSON/blob/main/schema/materialItem.yaml"
}
