{
  "condition": null,
  "creator": null,
  "description": "Socket an Artifact\u0027s [slot_trait] Trait Slot with this item to gain this trait:\\n\\nMaster of Time:\nAfter this creature manually {ACTION_casts} a single-target spell, the target\u0027s turn counter is increased by 5. This trait can only be applied to each creature once per battle.",
  "icon": "images/item/material/CounterclockwiseClock.png",
  "id": 1838,
  "name": "Counterclockwise Clock",
  "notes": [],
  "slot": "trait",
  "sources": [
    {
      "type": "random"
    }
  ],
  "stats": [],
  "trait": 2003
}