{
  "condition": null,
  "creator": null,
  "description": "Socket an Artifact\u0027s [slot_trait] Trait Slot with this item to gain this trait:\\n\\nSpotlight:\nAt the end of each enemy\u0027s turn, they {ACTION_attack} this creature for 15% normal damage and are afflicted with {CONDNAME_DEBUFF_CURSED}. This trait does not stack.",
  "icon": "images/item/material/DivaLace.png",
  "id": 1826,
  "name": "Diva Lace",
  "notes": [],
  "slot": "trait",
  "sources": [
    {
      "type": "random"
    }
  ],
  "stats": [],
  "trait": 2185
}