{
  "condition": null,
  "creator": null,
  "description": "Socket an Artifact\u0027s [slot_trait] Trait Slot with this item to gain this trait:\\n\\nSkyttels:\nAt the start of battle, this creature gains copies of your other creatures\u0027 permanent Spell Gems. This trait does not work on creatures that also have this trait.",
  "icon": "images/item/material/ParticleofDiamant.png",
  "id": 1083,
  "name": "Particle of Diamant",
  "notes": [],
  "slot": "trait",
  "sources": [
    {
      "type": "random"
    }
  ],
  "stats": [],
  "trait": 1048
}