{
  "condition": null,
  "creator": null,
  "description": "Socket an Artifact\u0027s [slot_trait] Trait Slot with this item to gain this trait:\\n\\nVelox:\nThis creature\u0027s first 3 permanent, stat-manipulating Spell Gems each have a 50% chance to be {ACTION_cast} automatically at the start of battle.",
  "icon": "images/item/material/SpiritEar.png",
  "id": 678,
  "name": "Spirit Ear",
  "notes": [],
  "slot": "trait",
  "sources": [
    {
      "type": "random"
    }
  ],
  "stats": [],
  "trait": 616
}