{
    "condition":  null,
    "creator":  null,
    "description":  "Socket an Artifact\u0027s [slot_trait] Trait Slot with this item to gain this trait:\\n\\nFollow The Leader:\nAfter an enemy is sent to the bottom of the {TIMELINE}, all other enemies each have a 5% chance to be sent to the bottom of the {TIMELINE} as well. This trait does not stack.",
    "icon":  "images/item/material/WizenedPitcher.png",
    "id":  1041,
    "name":  "Wizened Pitcher",
    "notes":  [

              ],
    "slot":  "trait",
    "sources":  [
                    {
                        "type":  "random"
                    }
                ],
    "stats":  [

              ],
    "trait":  1097,
    "$schema":  "https://github.com/iconmaster5326/SiralimJSON/blob/main/schema/materialItem.yaml"
}
