{
    "creator":  null,
    "id":  142,
    "name":  "Lonestar",
    "notes":  [

              ],
    "sources":  [

                ],
    "sprite":  {
                   "east":  [
                                "images/costume/Lonestar/overworld_e0.png",
                                "images/costume/Lonestar/overworld_e1.png"
                            ],
                   "north":  [
                                 "images/costume/Lonestar/overworld_n0.png",
                                 "images/costume/Lonestar/overworld_n1.png"
                             ],
                   "south":  [
                                 "images/costume/Lonestar/overworld_s0.png",
                                 "images/costume/Lonestar/overworld_s1.png"
                             ],
                   "west":  [
                                "images/costume/Lonestar/overworld_w0.png",
                                "images/costume/Lonestar/overworld_w1.png"
                            ]
               },
    "$schema":  "https://github.com/iconmaster5326/SiralimJSON/blob/main/schema/costume.yaml"
}
