{
    "advanced":  false,
    "ascendedPerk":  477,
    "costumes":  [
                     256,
                     445,
                     446
                 ],
    "creator":  null,
    "creatures":  [
                      67,
                      581
                  ],
    "decoration":  0,
    "description":  [
                        "Cabalists can conjure Spell Gems out of thin air to be used by their creatures at any given moment. These magi prefer to employ high-risk, high-reward battle strategies to ensure their victory.",
                        "As a Cabalist, you\u0027ll enable your creatures to cast spells that they normally wouldn\u0027t have access to. While other people\u0027s creatures might run out of Spell Gem Charges, you\u0027ll be able to keep your creatures well-stocked with fresh Spell Gems at the start of every battle."
                    ],
    "icon":  "images/spec/Cabalist.png",
    "id":  3,
    "name":  "Cabalist",
    "notes":  [

              ],
    "perks":  [
                  187,
                  191,
                  198,
                  197,
                  190,
                  194,
                  199,
                  196,
                  195,
                  189,
                  188,
                  193,
                  186,
                  192,
                  185
              ],
    "project":  47,
    "skin":  0,
    "spell":  388,
    "$schema":  "https://github.com/iconmaster5326/SiralimJSON/blob/main/schema/specialization.yaml"
}
