{
  "advanced": false,
  "ascendedPerk": 473,
  "costumes": [
    510,
    511,
    512
  ],
  "creator": null,
  "creatures": [
    47,
    128
  ],
  "decoration": 0,
  "description": [
    "Witch Doctors are spiritual warriors who cast deadly hexes and curses on their enemies, forcing them to fight against each other.",
    "As a Witch Doctor, you\u0027ll manipulate your foes into damaging each other and empowering your creatures to ensure victory."
  ],
  "icon": "images/spec/WitchDoctor.png",
  "id": 29,
  "name": "Witch Doctor",
  "notes": [],
  "perks": [
    416,
    408,
    418,
    415,
    405,
    411,
    409,
    404,
    413,
    406,
    412,
    417,
    407,
    414,
    410
  ],
  "project": 91,
  "skin": 0,
  "spell": 667
}