{
    "creator":  null,
    "creature":  1021,
    "description":  "The head ensures that enemies always have {CONDNAME_DEBUFF_BURNED}, and it increases the potency of this debuff. In addition, enemies cannot circumvent damage from {CONDNAME_DEBUFF_BURNED}.",
    "god":  null,
    "id":  1642,
    "item":  null,
    "name":  "Head of Nebodar",
    "notes":  [

              ],
    "race":  null,
    "$schema":  "https://github.com/iconmaster5326/SiralimJSON/blob/main/schema/trait.yaml"
}
