{
    "creator":  null,
    "creature":  934,
    "description":  "Your creatures\u0027 Spell Gems are 70% more potent when they have an odd number of {STAT_charges}, and are 70% less potent when they have an even number of {STAT_charges}. This trait does not stack.",
    "god":  null,
    "id":  1199,
    "item":  939,
    "name":  "Oscillation",
    "notes":  [

              ],
    "race":  null,
    "$schema":  "https://github.com/iconmaster5326/SiralimJSON/blob/main/schema/trait.yaml"
}
