{
    "creator":  null,
    "creature":  970,
    "description":  "After this creature {ACTION_attacks}, it gains 5% {STAT_attack}. After this creature {ACTION_casts} a spell, it gains 5% {STAT_intelligence}. After this creature {ACTION_defends}, it gains 5% {STAT_defense}. After this creature {ACTION_provokes}, it gains 5% {STAT_speed}.",
    "god":  null,
    "id":  1532,
    "item":  null,
    "name":  "Photomorphogenesis",
    "notes":  [

              ],
    "race":  null,
    "$schema":  "https://github.com/iconmaster5326/SiralimJSON/blob/main/schema/trait.yaml"
}
