{
    "battleSprite":  "images/creature/BismuthParagon/battle.png",
    "class":  "life",
    "creator":  null,
    "givesMana":  true,
    "god":  null,
    "id":  993,
    "item":  1319,
    "lore":  "This creature is the brightest of the Paragons, and the most ornate. This is because it is greatly skilled at working all kinds of minerals, including the one that is part of its body. However, it does not like working with small objects, and is dedicated exclusively to directing or working on large constructions, many of which have gone down in history for their size and beauty.",
    "menagerieDialog":  [
                            "Your Eminence, please allow me to rest for a bit. It\u0027s been a long day.",
                            "We must constantly re-evaluate our battle strategies to ensure that our foes can never get the best of us.",
                            "Everett is a liar. Don\u0027t say I didn\u0027t warn you.",
                            "Two Paragons make a King Paragon. Two King Paragons make a Gold Paragon. Two Gold Paragons make a Grandpa Paragon.\\n\\nWait, what?",
                            "Something is amiss. I cannot say what is wrong for certain, but I am unable to shake this feeling of dread."
                        ],
    "minDepth":  1,
    "name":  "Bismuth Paragon",
    "notes":  [

              ],
    "overworldSprite":  {
                            "east":  [
                                         "images/creature/BismuthParagon/overworld_e0.png",
                                         "images/creature/BismuthParagon/overworld_e1.png"
                                     ],
                            "north":  [
                                          "images/creature/BismuthParagon/overworld_n0.png",
                                          "images/creature/BismuthParagon/overworld_n1.png"
                                      ],
                            "south":  [
                                          "images/creature/BismuthParagon/overworld_s0.png",
                                          "images/creature/BismuthParagon/overworld_s1.png"
                                      ],
                            "west":  [
                                         "images/creature/BismuthParagon/overworld_w0.png",
                                         "images/creature/BismuthParagon/overworld_w1.png"
                                     ]
                        },
    "race":  "Paragon",
    "reserved":  false,
    "skins":  [

              ],
    "sources":  [
                    {
                        "desc":  "Life Guild Shop",
                        "type":  "special"
                    }
                ],
    "specializations":  [

                        ],
    "statGrowth":  {
                       "attack":  17,
                       "defense":  17,
                       "health":  42,
                       "intelligence":  17,
                       "speed":  17
                   },
    "trait":  1567,
    "$schema":  "https://github.com/iconmaster5326/SiralimJSON/blob/main/schema/creature.yaml"
}
