{
    "battleSprite":  "images/creature/CursedReaper/battle.png",
    "class":  "death",
    "creator":  null,
    "givesMana":  true,
    "god":  null,
    "id":  15,
    "item":  250,
    "lore":  "Just like Banshees, Reapers can be seen when a life is about to end, or when a catastrophe is about to occur. However, these creatures are silent and only move when death comes. As they have eternal life, these beings have been the target of numerous spells over the years. After being hit with a certain number of curses, their structure changes and they become Cursed Reapers, entities that bring bad luck to anyone who approaches them.",
    "menagerieDialog":  [
                            "Oh, hello there! Would you like to know the exact date of your death?",
                            "While I can\u0027t hold your hand, I will have your back.",
                            "(This creature always seems to be focused on something you can\u0027t see.)",
                            "Don\u0027t fear the reaper.\\n\\n(Sigh. How cliché.)",
                            "(Its inability to stop grinning is rather unsettling for you and your creatures.)"
                        ],
    "minDepth":  1,
    "name":  "Cursed Reaper",
    "notes":  [

              ],
    "overworldSprite":  {
                            "east":  [
                                         "images/creature/CursedReaper/overworld_e0.png",
                                         "images/creature/CursedReaper/overworld_e1.png"
                                     ],
                            "north":  [
                                          "images/creature/CursedReaper/overworld_n0.png",
                                          "images/creature/CursedReaper/overworld_n1.png"
                                      ],
                            "south":  [
                                          "images/creature/CursedReaper/overworld_s0.png",
                                          "images/creature/CursedReaper/overworld_s1.png"
                                      ],
                            "west":  [
                                         "images/creature/CursedReaper/overworld_w0.png",
                                         "images/creature/CursedReaper/overworld_w1.png"
                                     ]
                        },
    "race":  "Reaper",
    "reserved":  false,
    "skins":  [

              ],
    "sources":  [
                    {
                        "desc":  "God Shop (Tenebris)",
                        "type":  "special"
                    }
                ],
    "specializations":  [

                        ],
    "statGrowth":  {
                       "attack":  26,
                       "defense":  11,
                       "health":  31,
                       "intelligence":  16,
                       "speed":  21
                   },
    "trait":  160,
    "$schema":  "https://github.com/iconmaster5326/SiralimJSON/blob/main/schema/creature.yaml"
}
