{
    "battleSprite":  "images/creature/DiamondParagon/battle.png",
    "class":  "life",
    "creator":  null,
    "givesMana":  true,
    "god":  null,
    "id":  6,
    "item":  137,
    "lore":  "Paragons are extremely long-lived and intelligent creatures that are integrated into human society. They usually hold important positions as great merchants, notaries or even advisors to the sovereigns of Rodia.\\n\\nDiamond Paragons are especially interested in the fauna and flora of Rodia. When the war ended, many of them joined teams of biologists in different cities to study them. The University of Natural Science in Vanelin is currently directed by one of them.",
    "menagerieDialog":  [
                            "Your Eminence, please allow me to rest for a bit. It\u0027s been a long day.",
                            "We must constantly re-evaluate our battle strategies to ensure that our foes can never get the best of us.",
                            "Everett is a liar. Don\u0027t say I didn\u0027t warn you.",
                            "Two Paragons make a King Paragon. Two King Paragons make a Gold Paragon. Two Gold Paragons make a Grandpa Paragon.\\n\\nWait, what?",
                            "Something is amiss. I cannot say what is wrong for certain, but I am unable to shake this feeling of dread."
                        ],
    "minDepth":  1,
    "name":  "Diamond Paragon",
    "notes":  [

              ],
    "overworldSprite":  {
                            "east":  [
                                         "images/creature/DiamondParagon/overworld_e0.png",
                                         "images/creature/DiamondParagon/overworld_e1.png"
                                     ],
                            "north":  [
                                          "images/creature/DiamondParagon/overworld_n0.png",
                                          "images/creature/DiamondParagon/overworld_n1.png"
                                      ],
                            "south":  [
                                          "images/creature/DiamondParagon/overworld_s0.png",
                                          "images/creature/DiamondParagon/overworld_s1.png"
                                      ],
                            "west":  [
                                         "images/creature/DiamondParagon/overworld_w0.png",
                                         "images/creature/DiamondParagon/overworld_w1.png"
                                     ]
                        },
    "race":  "Paragon",
    "reserved":  false,
    "skins":  [

              ],
    "sources":  [
                    {
                        "realm":  9,
                        "type":  "realm"
                    },
                    {
                        "realm":  11,
                        "type":  "realm"
                    }
                ],
    "specializations":  [

                        ],
    "statGrowth":  {
                       "attack":  3,
                       "defense":  28,
                       "health":  38,
                       "intelligence":  13,
                       "speed":  28
                   },
    "trait":  45,
    "$schema":  "https://github.com/iconmaster5326/SiralimJSON/blob/main/schema/creature.yaml"
}
