{
  "battleSprite": "images/creature/EvernightShade/battle.png",
  "class": "death",
  "creator": null,
  "givesMana": true,
  "god": null,
  "id": 495,
  "item": 284,
  "lore": "The scientific community debated for centuries whether Shades are intelligent creatures. The advancement of magic and the development of more rigorous experimentation methods finally revealed the truth: though some of their actions are quite elaborate, they are instinctive creatures.\\n\\nEvernight Shades hide in the darkness, and are especially dangerous when the sun sets, or in places where light is scarce, as they are invisible to most creatures.",
  "menagerieDialog": [
    "(It appears calm, but you should never lower your guard around a creature known for its trickery.)",
    "(You could swear you saw this tricky little guy spying on you while you were in the privvy earlier.)",
    "(It reaches behind your ear and, with a sly wink, produces a coin.)",
    "(It disappears from your sight before sneaking up from behind and tickling you. Tee hee, stop that!)",
    "(It\u0027s methodically approaching each of your creatures and shouting \u0022BOO!\u0022 in their faces. You should probably release this creature from your service.)"
  ],
  "minDepth": 1,
  "name": "Evernight Shade",
  "notes": [],
  "overworldSprite": {
    "east": [
      "images/creature/EvernightShade/overworld_e0.png",
      "images/creature/EvernightShade/overworld_e1.png"
    ],
    "north": [
      "images/creature/EvernightShade/overworld_n0.png",
      "images/creature/EvernightShade/overworld_n1.png"
    ],
    "south": [
      "images/creature/EvernightShade/overworld_s0.png",
      "images/creature/EvernightShade/overworld_s1.png"
    ],
    "west": [
      "images/creature/EvernightShade/overworld_w0.png",
      "images/creature/EvernightShade/overworld_w1.png"
    ]
  },
  "race": "Shade",
  "reserved": false,
  "skins": [],
  "sources": [
    {
      "desc": "God Shop (Vertraag)",
      "type": "special"
    }
  ],
  "specializations": [],
  "statGrowth": {
    "attack": 21,
    "defense": 17,
    "health": 28,
    "intelligence": 16,
    "speed": 21
  },
  "trait": 200
}