{
  "battleSprite": "images/creature/PalaceFamiliar/battle.png",
  "class": "sorcery",
  "creator": null,
  "givesMana": true,
  "god": null,
  "id": 522,
  "item": 503,
  "lore": "After their rebellion, many Familiars went north and established a community in an old tower, inhabited only by Cornell and other Grimoires since the Apollinaire Massacre. There, they filled the looted shelves with books of science and magic.\\n\\nPalace Familiars are distinguished members of their community, who established the Council which decides on matters of trade, the provisioning of the tower, and Familiar activities. In battle, they throw their scepters at their enemies, then call their weapons back with telekinesis.",
  "menagerieDialog": [
    "I\u0027d rather work at the castle library than risk my life fighting beyond these steadfast walls.",
    "There is a lot of wasted space in this castle. Perhaps you should set up a library where we can research new spells.",
    "Did you know that an Eft can live for up to 20 days without water?",
    "(Its eyes scan its surroundings with innocent curiosity.)",
    "(Despite the fact that it can speak your language, this creature insists on hooting repeatedly to feign ignorance to whatever you tell it to do.)"
  ],
  "minDepth": 1,
  "name": "Palace Familiar",
  "notes": [],
  "overworldSprite": {
    "east": [
      "images/creature/PalaceFamiliar/overworld_e0.png",
      "images/creature/PalaceFamiliar/overworld_e1.png"
    ],
    "north": [
      "images/creature/PalaceFamiliar/overworld_n0.png",
      "images/creature/PalaceFamiliar/overworld_n1.png"
    ],
    "south": [
      "images/creature/PalaceFamiliar/overworld_s0.png",
      "images/creature/PalaceFamiliar/overworld_s1.png"
    ],
    "west": [
      "images/creature/PalaceFamiliar/overworld_w0.png",
      "images/creature/PalaceFamiliar/overworld_w1.png"
    ]
  },
  "race": "Familiar",
  "reserved": false,
  "skins": [],
  "sources": [
    {
      "desc": "God Shop (Zonte)",
      "type": "special"
    }
  ],
  "specializations": [],
  "statGrowth": {
    "attack": 16,
    "defense": 16,
    "health": 32,
    "intelligence": 26,
    "speed": 16
  },
  "trait": 417
}