{
    "battleSprite":  "images/creature/PlagueScholar/battle.png",
    "class":  "sorcery",
    "creator":  null,
    "givesMana":  true,
    "god":  null,
    "id":  575,
    "item":  730,
    "lore":  "When the city of Andolin was quarantined because of a terrible disease, Plague Doctors began to appear mysteriously. In less than a week, they healed the sick and disappeared as quickly as they arrived.\\n\\nSome wounds or illnesses are too serious for even a Plague Doctor to heal. The Plague Scholar knows when to give up, but before doing so it prepares a potion that emotionally relaxes the sick person and their closest people so that they can calmly accept what is to come.",
    "menagerieDialog":  [
                            "Bend over, grab your ankles, and cough!",
                            "(It points at you, then mimes a drinking motion. Unsure about how to respond, you pretend to be distracted by another one of your creatures.)",
                            "(It hands you a vial full of purple liquid. You shake your head as if to reject its offer, and it glances downward with a sad look on its face.)",
                            "(It picks its nose, but it\u0027s not really gross because its nose is a mask. Pretty neat.)",
                            "(It was busy mixing a potion before you startled it and caused it to drop its vials on the ground.)"
                        ],
    "minDepth":  1,
    "name":  "Plague Scholar",
    "notes":  [

              ],
    "overworldSprite":  {
                            "east":  [
                                         "images/creature/PlagueScholar/overworld_e0.png",
                                         "images/creature/PlagueScholar/overworld_e1.png"
                                     ],
                            "north":  [
                                          "images/creature/PlagueScholar/overworld_n0.png",
                                          "images/creature/PlagueScholar/overworld_n1.png"
                                      ],
                            "south":  [
                                          "images/creature/PlagueScholar/overworld_s0.png",
                                          "images/creature/PlagueScholar/overworld_s1.png"
                                      ],
                            "west":  [
                                         "images/creature/PlagueScholar/overworld_w0.png",
                                         "images/creature/PlagueScholar/overworld_w1.png"
                                     ]
                        },
    "race":  "Plague Doctor",
    "reserved":  false,
    "skins":  [

              ],
    "sources":  [
                    {
                        "desc":  "God Shop (4080)",
                        "type":  "special"
                    }
                ],
    "specializations":  [

                        ],
    "statGrowth":  {
                       "attack":  14,
                       "defense":  17,
                       "health":  34,
                       "intelligence":  19,
                       "speed":  22
                   },
    "trait":  669,
    "$schema":  "https://github.com/iconmaster5326/SiralimJSON/blob/main/schema/creature.yaml"
}
