{
  "battleSprite": "images/creature/Syringe/battle.png",
  "class": "death",
  "creator": null,
  "givesMana": true,
  "god": null,
  "id": 1436,
  "item": 1710,
  "lore": "The origin of this creature is a complete mystery. The first one appeared suddenly in a crowded street in Siralim, and it stayed there, completely still, until the authorities took it away. When the Rodian government allowed further study, it was discovered that the creature was an empty shell\u00E2\u20AC\u201Dnothing inside. Since then, more have appeared across the continent, with no one understanding how or why. A simple spell is all it takes to control them like puppets.",
  "menagerieDialog": [
    "I do not wish to speak to you right now. I would prefer to return to where I came from.",
    "You would dare to rip me from my portal and summon me to this dying world? You have no shame.",
    "I am bound to serve you, but know that it is not by choice.",
    "I do not belong here in your filthy Menagerie. I deserve my own quarters in your castle!",
    "Give me freedom, or give me death!"
  ],
  "minDepth": 1,
  "name": "Syringe",
  "notes": [],
  "overworldSprite": {
    "east": [
      "images/creature/Syringe/overworld_e0.png",
      "images/creature/Syringe/overworld_e1.png"
    ],
    "north": [
      "images/creature/Syringe/overworld_n0.png",
      "images/creature/Syringe/overworld_n1.png"
    ],
    "south": [
      "images/creature/Syringe/overworld_s0.png",
      "images/creature/Syringe/overworld_s1.png"
    ],
    "west": [
      "images/creature/Syringe/overworld_w0.png",
      "images/creature/Syringe/overworld_w1.png"
    ]
  },
  "race": "Exotic",
  "reserved": true,
  "skins": [],
  "sources": [
    {
      "desc": "Otherworld Portals",
      "type": "special"
    }
  ],
  "specializations": [],
  "statGrowth": {
    "attack": 25,
    "defense": 15,
    "health": 30,
    "intelligence": 25,
    "speed": 15
  },
  "trait": 2052
}