{
  "battleSprite": "images/creature/VolatilePhoenix/battle.png",
  "class": "sorcery",
  "creator": null,
  "givesMana": true,
  "god": null,
  "id": 59,
  "item": 434,
  "lore": "Phoenixes are birds that only lay one egg during each of their life cycles. The eggs take six months to open and must be incubated under very strict conditions for the chick to develop successfully.\\n\\nThe Volatile Phoenix is the fastest and most skilled of its kind. It can plummet and swerve sharply at the last moment, casting a powerful spell on its enemies.",
  "menagerieDialog": [
    "(It\u0027s preening its feathers, plucking out the ones that are damaged from battle.)",
    "(It screeches and spreads its wings, showering you in a coat of dusty ash.)",
    "(It\u0027s closely studying its environment, as if trying to note where every single object in your castle is located.)",
    "(You are confident that a Phoenix\u0027s so-called resurrection is merely a parlor trick. Whenever it \u0022revives\u0022, it seems to have no recollection of its past life. Someone is probably just replacing this creature with a new one when it dies.)",
    "(It gently pecks at your hand. Perhaps it\u0027s hungry. But what do Phoenixes even eat?)"
  ],
  "minDepth": 1,
  "name": "Volatile Phoenix",
  "notes": [],
  "overworldSprite": {
    "east": [
      "images/creature/VolatilePhoenix/overworld_e0.png",
      "images/creature/VolatilePhoenix/overworld_e1.png"
    ],
    "north": [
      "images/creature/VolatilePhoenix/overworld_n0.png",
      "images/creature/VolatilePhoenix/overworld_n1.png"
    ],
    "south": [
      "images/creature/VolatilePhoenix/overworld_s0.png",
      "images/creature/VolatilePhoenix/overworld_s1.png"
    ],
    "west": [
      "images/creature/VolatilePhoenix/overworld_w0.png",
      "images/creature/VolatilePhoenix/overworld_w1.png"
    ]
  },
  "race": "Phoenix",
  "reserved": false,
  "skins": [],
  "sources": [
    {
      "realm": 11,
      "type": "realm"
    },
    {
      "realm": 27,
      "type": "realm"
    }
  ],
  "specializations": [],
  "statGrowth": {
    "attack": 21,
    "defense": 11,
    "health": 31,
    "intelligence": 21,
    "speed": 21
  },
  "trait": 349
}