{
    "creator":  null,
    "id":  223,
    "name":  "Astral Gallery Landscape",
    "notes":  [

              ],
    "sources":  [
                    {
                        "cost":  5,
                        "rank":  23,
                        "realm":  31,
                        "type":  "godshop"
                    }
                ],
    "sprite":  "images/bg/AstralGalleryLandscape.png",
    "$schema":  "https://github.com/iconmaster5326/SiralimJSON/blob/main/schema/background.yaml"
}
